PipelinedWithFPU/float_to_integer.v
module float_to_integer(
  input[31:0]      a,
  output reg[31:0] d,
  output reg       p_lost,
  output           denorm,
  output reg       invalid
);

wire hidden_bit = |a[30:23]; // 0.XXX if exponent is zero otherwire, 1.XXX
wire frac_is_not_0 = |a[22:0];
assign denorm = ~hidden_bit & frac_is_not_0;
wire is_zero = ~hidden_bit & ~frac_is_not_0;
wire sign = a[31];
wire[8:0] shift_right_bits = 9'd158 - {1'b0, a[30:23]};
wire[55:0] frac0 = {hidden_bit, a[22:0], 32'h0};
wire[55:0] f_abs = (shift_right_bits > 9'd32) ? frac0 >> 6'd32 : frac0 >> shift_right_bits;
wire lost_bits = |f_abs[23:0];
wire[31:0] int32 = sign ? ~f_abs[55:24] + 32'd1 : f_abs[55:24];
always @* begin
  if(denorm) begin
    p_lost = 1;
    invalid = 0;
    d = 32'h0;
  end else begin
    if(shift_right_bits[8]) begin // too big
      p_lost = 0;
      invalid = 1;
      d = 32'h80000000;
    end else begin
      if(shift_right_bits[7:0] > 8'h1f) begin // too small
        if(is_zero)
          p_lost = 0;
        else
          p_lost = 1;
        invalid = 0;
        d = 32'h0;
      end else begin
        if(sign != int32[31]) begin
          p_lost = 0;
          invalid = 1;
          d = 32'h80000000;
        end else begin
          if(lost_bits)
            p_lost = 1;
          else
            p_lost = 0;
          invalid = 0;
          d = int32;
        end
      end
    end
  end
end

endmodule

FloatingPoint/float_to_integer_tb.v
`timescale 1ns/1ns
module float_to_integer_tb;

reg[31:0] a;
wire[31:0] d;
wire p_lost, denorm, invalid;
float_to_integer f2i(a, d, p_lost, denorm, invalid);
initial begin
     a = 32'h4effffff;
  #1 a = 32'h4f000000;
  #1 a = 32'h3f800000;
  #1 a = 32'h3f000000;
  #1 a = 32'h00000001;
  #1 a = 32'h7f800000;
  #1 a = 32'h3fc00000;
  #1 a = 32'hcf000000;
  #1 a = 32'hcf000001;
  #1 a = 32'hbf800000;
  #1 a = 32'hbf7fffff;
  #1 a = 32'h80000001;
  #1 a = 32'hff800000;
  #1 a = 32'h00000000;
  #1 $finish;
end
initial begin
  $dumpfile("float_to_integer.vcd");
  $dumpvars;
end

endmodule

FloatingPoint/float_to_integer.vcd
$date
	Tue May 19 23:54:05 2020
$end
$version
	Icarus Verilog
$end
$timescale
	1ns
$end
$scope module float_to_integer_tb $end
$var wire 1 ! p_lost $end
$var wire 1 " invalid $end
$var wire 1 # denorm $end
$var wire 32 $ d [31:0] $end
$var reg 32 % a [31:0] $end
$scope module f2i $end
$var wire 32 & a [31:0] $end
$var wire 1 # denorm $end
$var wire 1 ' is_zero $end
$var wire 1 ( sign $end
$var wire 9 ) shift_right_bits [8:0] $end
$var wire 1 * lost_bits $end
$var wire 32 + int32 [31:0] $end
$var wire 1 , hidden_bit $end
$var wire 1 - frac_is_not_0 $end
$var wire 56 . frac0 [55:0] $end
$var wire 56 / f_abs [55:0] $end
$var reg 32 0 d [31:0] $end
$var reg 1 " invalid $end
$var reg 1 ! p_lost $end
$upscope $end
$upscope $end
$enddefinitions $end
#0
$dumpvars
b1111111111111111111111110000000 0
b1111111111111111111111110000000000000000000000000000000 /
b11111111111111111111111100000000000000000000000000000000 .
1-
1,
b1111111111111111111111110000000 +
0*
b1 )
0(
0'
b1001110111111111111111111111111 &
b1001110111111111111111111111111 %
b1111111111111111111111110000000 $
0#
0"
0!
$end
#1
b10000000000000000000000000000000 $
b10000000000000000000000000000000 0
1"
b10000000000000000000000000000000 +
b10000000000000000000000000000000000000000000000000000000 /
0-
b0 )
b10000000000000000000000000000000000000000000000000000000 .
b1001111000000000000000000000000 %
b1001111000000000000000000000000 &
#2
b1 $
b1 0
0"
b1 +
b1000000000000000000000000 /
b11111 )
b111111100000000000000000000000 %
b111111100000000000000000000000 &
#3
b0 +
1*
b100000000000000000000000 /
b0 $
b0 0
1!
b100000 )
b111111000000000000000000000000 %
b111111000000000000000000000000 &
#4
1#
b1 /
0,
1-
b10011110 )
b100000000000000000000000000000000 .
b1 %
b1 &
#5
b10000000000000000000000000000000 $
b10000000000000000000000000000000 0
1"
0!
b100000000000000000000000 /
0#
1,
0-
b110011111 )
b10000000000000000000000000000000000000000000000000000000 .
b1111111100000000000000000000000 %
b1111111100000000000000000000000 &
#6
b1 +
b1100000000000000000000000 /
b1 $
b1 0
0"
1!
1-
b11111 )
b11000000000000000000000000000000000000000000000000000000 .
b111111110000000000000000000000 %
b111111110000000000000000000000 &
#7
0*
b10000000000000000000000000000000 +
b10000000000000000000000000000000 $
b10000000000000000000000000000000 0
0"
0!
b10000000000000000000000000000000000000000000000000000000 /
0-
1(
b0 )
b10000000000000000000000000000000000000000000000000000000 .
b11001111000000000000000000000000 %
b11001111000000000000000000000000 &
#8
1"
b1111111111111111111111100000000 +
b10000000000000000000000100000000000000000000000000000000 /
1-
b10000000000000000000000100000000000000000000000000000000 .
b11001111000000000000000000000001 %
b11001111000000000000000000000001 &
#9
b11111111111111111111111111111111 $
b11111111111111111111111111111111 0
0"
b11111111111111111111111111111111 +
b1000000000000000000000000 /
0-
b11111 )
b10000000000000000000000000000000000000000000000000000000 .
b10111111100000000000000000000000 %
b10111111100000000000000000000000 &
#10
b0 +
1*
b0 $
b0 0
1!
b111111111111111111111111 /
1-
b100000 )
b11111111111111111111111100000000000000000000000000000000 .
b10111111011111111111111111111111 %
b10111111011111111111111111111111 &
#11
1#
b1 /
0,
b10011110 )
b100000000000000000000000000000000 .
b10000000000000000000000000000001 %
b10000000000000000000000000000001 &
#12
b10000000000000000000000000000000 $
b10000000000000000000000000000000 0
1"
0!
b100000000000000000000000 /
0#
1,
0-
b110011111 )
b10000000000000000000000000000000000000000000000000000000 .
b11111111100000000000000000000000 %
b11111111100000000000000000000000 &
#13
0*
b0 /
1'
b0 $
b0 0
0"
0!
b0 .
0,
0(
b10011110 )
b0 %
b0 &
