FloatingPoint/pipelined_float_adder.v
module pipelined_float_adder(
  input[31:0]  a,
  input[31:0]  b,
  input        sub,
  input[1:0]   rm,
  output[31:0] s,
  input        clk,
  input        clrn,
  input        e
);

wire[26:0] a_small_frac;
wire[23:0] a_large_frac;
wire[22:0] a_inf_nan_frac;
wire[7:0]  a_exp;
wire       a_is_nan, a_is_inf, a_sign, a_op_sub;

float_adder_align_stage align_stage(
  a, b, sub, a_is_nan, a_is_inf, a_inf_nan_frac, a_sign,
  a_exp, a_op_sub, a_large_frac, a_small_frac);

wire[1:0]  c_rm;
wire[26:0] c_small_frac;
wire[27:0] c_frac;
wire[23:0] c_large_frac;
wire[22:0] c_inf_nan_frac;
wire[7:0]  c_exp;
wire c_is_nan, c_is_inf, c_sign, c_op_sub;

float_adder_align_cal_reg align_cal_reg(
  rm, a_is_nan, a_is_inf, a_inf_nan_frac,
  a_sign, a_exp, a_op_sub, a_large_frac, a_small_frac,
  clk, clrn, e,
  c_rm, c_is_nan, c_is_inf, c_inf_nan_frac,
  c_sign, c_exp, c_op_sub, c_large_frac, c_small_frac);

float_adder_cal_stage cal_stage(
  c_op_sub, c_large_frac, c_small_frac, c_frac);

wire[1:0] n_rm;
wire[22:0] n_inf_nan_frac;
wire[7:0] n_exp;
wire[27:0] n_frac;
wire n_is_nan, n_is_inf, n_sign;

float_adder_cal_norm_reg cal_norm_reg(
  c_rm, c_is_nan, c_is_inf, c_inf_nan_frac, c_sign, c_exp, c_frac,
  clk, clrn, e,
  n_rm, n_is_nan, n_is_inf, n_inf_nan_frac, n_sign, n_exp, n_frac);

float_adder_norm_stage norm_stage(
  n_rm, n_is_nan, n_is_inf, n_inf_nan_frac, n_sign, n_exp, n_frac, s);

endmodule

module float_adder_align_stage(
  input[31:0]  a,
  input[31:0]  b,
  input        sub,
  output       a_is_nan,
  output       a_is_inf,
  output[22:0] a_inf_nan_frac,
  output       a_sign,
  output[7:0]  a_exp,
  output       a_op_sub,
  output[23:0] a_large_frac,
  output[26:0] a_small_frac
);
wire exchange = (b[30:0] > a[30:0]);
wire[31:0] fp_large = exchange ? b : a;
wire[31:0] fp_small = exchange ? a : b;
wire       fp_large_hidden_bit = |fp_large[30:23];
wire       fp_small_hidden_bit = |fp_small[30:23];
wire[23:0] large_frac24 = {fp_large_hidden_bit, fp_large[22:0]};
wire[23:0] small_frac24 = {fp_small_hidden_bit, fp_small[22:0]};
assign a_exp = fp_large[30:23];
assign a_sign = exchange ? sub ^ b[31] : a[31];
assign a_op_sub = sub ^ fp_large[31] ^ fp_small[31];
wire fp_large_expo_is_ff = &fp_large[30:23]; // exp == 0xff
wire fp_small_expo_is_ff = &fp_small[30:23];
wire fp_large_frac_is_00 = ~|fp_large[22:0]; // frac == 0x0
wire fp_small_frac_is_00 = ~|fp_small[22:0];
wire fp_large_is_inf = fp_large_expo_is_ff & fp_large_frac_is_00;
wire fp_small_is_inf = fp_small_expo_is_ff & fp_small_frac_is_00;
wire fp_large_is_nan = fp_large_expo_is_ff & ~fp_large_frac_is_00;
wire fp_small_is_nan = fp_small_expo_is_ff & ~fp_small_frac_is_00;
assign a_is_inf = fp_large_is_inf | fp_small_is_inf;
assign a_is_nan = fp_large_is_nan | fp_small_is_nan |
                  ((sub ^ fp_small[31] ^ fp_large[31]) & fp_large_is_inf & fp_small_is_inf);
wire[22:0] nan_frac = (a[21:0] > b[21:0]) ? {1'b1, a[21:0]} : {1'b1, b[21:0]};
assign a_inf_nan_frac = a_is_nan ? nan_frac : 23'h0;
wire[7:0] exp_diff = fp_large[30:23] - fp_small[30:23];
wire      small_den_only = (fp_large[30:23] != 0) & (fp_small[30:23] == 0);
wire[7:0] shift_amount = small_den_only ? exp_diff - 8'h1 : exp_diff;
wire[49:0] small_frac50 = (shift_amount >= 26) ? {26'h0, small_frac24} : {small_frac24, 26'h0} >> shift_amount;
assign a_large_frac = large_frac24;
assign a_small_frac = {small_frac50[49:24], |small_frac50[23:0]};
endmodule

module float_adder_align_cal_reg(
  input[1:0]  rm,
  input       a_is_nan,
  input       a_is_inf,
  input[22:0] a_inf_nan_frac,
  input       a_sign,
  input[7:0]  a_exp,
  input       a_op_sub,
  input[23:0] a_large_frac,
  input[26:0] a_small_frac,
  input       clk,
  input       clrn,
  input       e,
  output reg[1:0]  c_rm,
  output reg       c_is_nan,
  output reg       c_is_inf,
  output reg[22:0] c_inf_nan_frac,
  output reg       c_sign,
  output reg[7:0]  c_exp,
  output reg       c_op_sub,
  output reg[23:0] c_large_frac,
  output reg[26:0] c_small_frac
);
always @(posedge clk or negedge clrn) begin
  if(!clrn) begin
    c_rm <= 0;
    c_is_nan <= 0;
    c_is_inf <= 0;
    c_inf_nan_frac <= 0;
    c_sign <= 0;
    c_exp <= 0;
    c_op_sub <= 0;
    c_large_frac <= 0;
    c_small_frac <= 0;
  end else if(e) begin
    c_rm <= rm;
    c_is_nan <= a_is_nan;
    c_is_inf <= a_is_inf;
    c_inf_nan_frac <= a_inf_nan_frac;
    c_sign <= a_sign;
    c_exp <= a_exp;
    c_op_sub <= a_op_sub;
    c_large_frac <= a_large_frac;
    c_small_frac <= a_small_frac;
  end
end
endmodule

module float_adder_cal_stage(
  input        op_sub,
  input [23:0] large_frac,
  input [26:0] small_frac,
  output[27:0] cal_frac
);
wire[27:0] aligned_large_frac = {1'b0, large_frac, 3'b000};
wire[27:0] aligned_small_frac = {1'b0, small_frac};
assign cal_frac = op_sub ?
                  aligned_large_frac - aligned_small_frac :
                  aligned_large_frac + aligned_small_frac;
endmodule

module float_adder_cal_norm_reg(
  input[1:0]  c_rm,
  input       c_is_nan,
  input       c_is_inf,
  input[22:0] c_inf_nan_frac,
  input       c_sign,
  input[7:0]  c_exp,
  input[27:0] c_frac,
  input       clk,
  input       clrn,
  input       e,
  output reg[1:0]  n_rm,
  output reg       n_is_nan,
  output reg       n_is_inf,
  output reg[22:0] n_inf_nan_frac,
  output reg       n_sign,
  output reg[7:0]  n_exp,
  output reg[27:0] n_frac
);
always @(posedge clk or negedge clrn) begin
  if(!clrn) begin
    n_rm <= 0;
    n_is_nan <= 0;
    n_is_inf <= 0;
    n_inf_nan_frac <= 0;
    n_sign <= 0;
    n_exp <= 0;
    n_frac <= 0;
  end else if(e) begin
    n_rm <= c_rm;
    n_is_nan <= c_is_nan;
    n_is_inf <= c_is_inf;
    n_inf_nan_frac <= c_inf_nan_frac;
    n_sign <= c_sign;
    n_exp <= c_exp;
    n_frac <= c_frac;
  end
end
endmodule

module float_adder_norm_stage(
  input[1:0]  n_rm,
  input       n_is_nan,
  input       n_is_inf,
  input[22:0] n_inf_nan_frac,
  input       n_sign,
  input[7:0]  n_exp,
  input[27:0] n_frac,
  output[31:0] s
);
wire[26:0] f4, f3, f2, f1, f0;
wire[4:0] zeros;
assign zeros[4] = ~|n_frac[26:11]; // 16 bit shift
assign f4 = zeros[4] ? {n_frac[10:0], 16'b0} : n_frac[26:0];
assign zeros[3] = ~|f4[26:19];     // 8 bit shift
assign f3 = zeros[3] ? {f4[18:0], 8'b0} : f4;
assign zeros[2] = ~|f3[26:23];     // 4 bit shift
assign f2 = zeros[2] ? {f3[22:0], 4'b0} : f3;
assign zeros[1] = ~|f2[26:25];     // 2 bit shift
assign f1 = zeros[1] ? {f2[24:0], 2'b0} : f2;
assign zeros[0] = ~f1[26];         // 1 bit shift
assign f0 = zeros[0] ? {f1[25:0], 1'b0} : f1;
reg[26:0] frac0;
reg[7:0]  exp0;
always @* begin
  if(n_frac[27]) begin // 1x.xxxxxxxx
    frac0 = n_frac[27:0];
    exp0 = n_exp + 8'h1;
  end else begin
    if((n_exp > zeros) && (f0[26])) begin // 01.xxxxxx
      exp0 = n_exp - zeros;
      frac0 = f0;
    end else begin // denormalized or zero
      exp0 = 0;
      if(n_exp != 0)
        frac0 = n_frac[26:0] << (n_exp - 8'h1);
      else
        frac0 = n_frac[26:0];
    end
  end
end
wire frac_plus_1 = (n_rm == 2'b00 & frac0[3:0] == 4'b1100) |
                   (n_rm == 2'b00 & frac0[2] & (frac0[1] | frac0[0])) |
                   (n_rm == 2'b01 & (|frac0[2:0]) & n_sign) |
                   (n_rm == 2'b10 & (|frac0[2:0]) & ~n_sign);
wire[24:0] frac_round = {1'b0, frac0[26:3]} + frac_plus_1;
wire[7:0]  exponent = frac_round[24] ? exp0 + 8'h1 : exp0;
wire overflow = &exp0 | &exponent;
assign s = final_result(overflow, n_rm, n_sign, n_is_nan, n_is_inf, exponent, frac_round[22:0], n_inf_nan_frac);
function [31:0] final_result;
  input overflow;
  input[1:0] rm;
  input sign, is_nan, is_inf;
  input[7:0] exponent;
  input[22:0] fraction, inf_nan_frac;
  casex({overflow, rm, sign, is_nan, is_inf})
    6'b1_00_x_0_x : final_result = {sign,8'hff,23'h000000};   // inf
    6'b1_01_0_0_x : final_result = {sign,8'hfe,23'h7fffff};   // max
    6'b1_01_1_0_x : final_result = {sign,8'hff,23'h000000};   // inf
    6'b1_10_0_0_x : final_result = {sign,8'hff,23'h000000};   // inf
    6'b1_10_1_0_x : final_result = {sign,8'hfe,23'h7fffff};   // max
    6'b1_11_x_0_x : final_result = {sign,8'hfe,23'h7fffff};   // max
    6'b0_xx_x_0_0 : final_result = {sign,exponent,fraction};  // nor
    6'bx_xx_x_1_x : final_result = {1'b1,8'hff,inf_nan_frac}; // nan
    6'bx_xx_x_0_1 : final_result = {sign,8'hff,inf_nan_frac}; // inf
    default       : final_result = {sign,8'h00,23'h000000};   // 0
  endcase
endfunction
endmodule

FloatingPoint/pipelined_float_adder_tb.v
`timescale 1ns/1ns
module pipelined_fadder_tb;
reg  [31:0] a, b;
reg         sub;
reg         e;
reg  [1:0]  rm;
reg         clk, clrn;
wire [31:0] s;
pipelined_float_adder fadder(a,b,sub,rm,s,clk,clrn,e);
initial begin
      a    = 32'h3c600011;
      b    = 32'hbe820000;
      e    = 1;
      clk  = 1;
      clrn = 0;
      rm   = 0;
      sub  = 1;
  #2  clrn = 1;
  #13 rm   = 2'h1;
  #10 rm   = 2'h2;
  #10 rm   = 2'h3;
  #10 rm   = 2'h0;
      sub  = 0;
  #10 rm   = 2'h1;
  #10 rm   = 2'h2;
  #10 rm   = 2'h3;
  #10 rm   = 2'h0;
      sub  = 1;
      a    = 32'h3fffffff;
      b    = 32'hb3800000;
  #10 rm   = 2'h1;
  #10 rm   = 2'h2;
  #10 rm   = 2'h3;
  #10 rm   = 2'h0;
      sub  = 0;
  #10 rm   = 2'h1;
  #10 rm   = 2'h2;
  #10 rm   = 2'h3;
  #10 rm   = 2'h0;
      a    = 32'h7f800000;
      b    = 32'h7f800000;
  #10 sub  = 1;
  #10 sub  = 0;
      a    = 32'h7f00ffff;
      b    = 32'h7fe0000f;
  #10 sub  = 0;
      a    = 32'h7f7fffff;
      b    = 32'h7f7fffff;
  #10 sub  = 0;
      a    = 32'h7f00ffff;
      b    = 32'h00000000;
  #10 sub  = 0;
      a    = 32'h00800000;
      b    = 32'h007fffff;
  #10 sub  = 0;
      a    = 32'h00000007;
      b    = 32'h00000008;
  #10 sub  = 1;
  $finish;
end
always #5 clk = !clk;
initial begin
  $dumpfile("pipelined_float_adder.vcd");
  $dumpvars;
end
endmodule

FloatingPoint/pipelined_float_adder.vcd
$date
	Thu May 21 01:11:18 2020
$end
$version
	Icarus Verilog
$end
$timescale
	1ns
$end
$scope module pipelined_fadder_tb $end
$var wire 32 ! s [31:0] $end
$var reg 32 " a [31:0] $end
$var reg 32 # b [31:0] $end
$var reg 1 $ clk $end
$var reg 1 % clrn $end
$var reg 1 & e $end
$var reg 2 ' rm [1:0] $end
$var reg 1 ( sub $end
$scope module fadder $end
$var wire 32 ) a [31:0] $end
$var wire 32 * b [31:0] $end
$var wire 1 $ clk $end
$var wire 1 % clrn $end
$var wire 1 & e $end
$var wire 2 + rm [1:0] $end
$var wire 1 ( sub $end
$var wire 32 , s [31:0] $end
$var wire 1 - n_sign $end
$var wire 2 . n_rm [1:0] $end
$var wire 1 / n_is_nan $end
$var wire 1 0 n_is_inf $end
$var wire 23 1 n_inf_nan_frac [22:0] $end
$var wire 28 2 n_frac [27:0] $end
$var wire 8 3 n_exp [7:0] $end
$var wire 27 4 c_small_frac [26:0] $end
$var wire 1 5 c_sign $end
$var wire 2 6 c_rm [1:0] $end
$var wire 1 7 c_op_sub $end
$var wire 24 8 c_large_frac [23:0] $end
$var wire 1 9 c_is_nan $end
$var wire 1 : c_is_inf $end
$var wire 23 ; c_inf_nan_frac [22:0] $end
$var wire 28 < c_frac [27:0] $end
$var wire 8 = c_exp [7:0] $end
$var wire 27 > a_small_frac [26:0] $end
$var wire 1 ? a_sign $end
$var wire 1 @ a_op_sub $end
$var wire 24 A a_large_frac [23:0] $end
$var wire 1 B a_is_nan $end
$var wire 1 C a_is_inf $end
$var wire 23 D a_inf_nan_frac [22:0] $end
$var wire 8 E a_exp [7:0] $end
$scope module align_cal_reg $end
$var wire 1 $ clk $end
$var wire 1 % clrn $end
$var wire 1 & e $end
$var wire 2 F rm [1:0] $end
$var wire 27 G a_small_frac [26:0] $end
$var wire 1 ? a_sign $end
$var wire 1 @ a_op_sub $end
$var wire 24 H a_large_frac [23:0] $end
$var wire 1 B a_is_nan $end
$var wire 1 C a_is_inf $end
$var wire 23 I a_inf_nan_frac [22:0] $end
$var wire 8 J a_exp [7:0] $end
$var reg 8 K c_exp [7:0] $end
$var reg 23 L c_inf_nan_frac [22:0] $end
$var reg 1 : c_is_inf $end
$var reg 1 9 c_is_nan $end
$var reg 24 M c_large_frac [23:0] $end
$var reg 1 7 c_op_sub $end
$var reg 2 N c_rm [1:0] $end
$var reg 1 5 c_sign $end
$var reg 27 O c_small_frac [26:0] $end
$upscope $end
$scope module align_stage $end
$var wire 32 P a [31:0] $end
$var wire 1 C a_is_inf $end
$var wire 1 B a_is_nan $end
$var wire 24 Q a_large_frac [23:0] $end
$var wire 1 @ a_op_sub $end
$var wire 32 R b [31:0] $end
$var wire 1 S fp_large_is_inf $end
$var wire 1 T fp_large_is_nan $end
$var wire 1 U fp_small_is_inf $end
$var wire 1 V fp_small_is_nan $end
$var wire 1 W small_den_only $end
$var wire 1 ( sub $end
$var wire 50 X small_frac50 [49:0] $end
$var wire 24 Y small_frac24 [23:0] $end
$var wire 8 Z shift_amount [7:0] $end
$var wire 23 [ nan_frac [22:0] $end
$var wire 24 \ large_frac24 [23:0] $end
$var wire 1 ] fp_small_hidden_bit $end
$var wire 1 ^ fp_small_frac_is_00 $end
$var wire 1 _ fp_small_expo_is_ff $end
$var wire 32 ` fp_small [31:0] $end
$var wire 1 a fp_large_hidden_bit $end
$var wire 1 b fp_large_frac_is_00 $end
$var wire 1 c fp_large_expo_is_ff $end
$var wire 32 d fp_large [31:0] $end
$var wire 8 e exp_diff [7:0] $end
$var wire 1 f exchange $end
$var wire 27 g a_small_frac [26:0] $end
$var wire 1 ? a_sign $end
$var wire 23 h a_inf_nan_frac [22:0] $end
$var wire 8 i a_exp [7:0] $end
$upscope $end
$scope module cal_norm_reg $end
$var wire 8 j c_exp [7:0] $end
$var wire 23 k c_inf_nan_frac [22:0] $end
$var wire 1 : c_is_inf $end
$var wire 1 9 c_is_nan $end
$var wire 2 l c_rm [1:0] $end
$var wire 1 5 c_sign $end
$var wire 1 $ clk $end
$var wire 1 % clrn $end
$var wire 1 & e $end
$var wire 28 m c_frac [27:0] $end
$var reg 8 n n_exp [7:0] $end
$var reg 28 o n_frac [27:0] $end
$var reg 23 p n_inf_nan_frac [22:0] $end
$var reg 1 0 n_is_inf $end
$var reg 1 / n_is_nan $end
$var reg 2 q n_rm [1:0] $end
$var reg 1 - n_sign $end
$upscope $end
$scope module cal_stage $end
$var wire 24 r large_frac [23:0] $end
$var wire 1 7 op_sub $end
$var wire 27 s small_frac [26:0] $end
$var wire 28 t cal_frac [27:0] $end
$var wire 28 u aligned_small_frac [27:0] $end
$var wire 28 v aligned_large_frac [27:0] $end
$upscope $end
$scope module norm_stage $end
$var wire 1 w frac_plus_1 $end
$var wire 8 x n_exp [7:0] $end
$var wire 28 y n_frac [27:0] $end
$var wire 23 z n_inf_nan_frac [22:0] $end
$var wire 1 0 n_is_inf $end
$var wire 1 / n_is_nan $end
$var wire 2 { n_rm [1:0] $end
$var wire 1 - n_sign $end
$var wire 1 | overflow $end
$var wire 5 } zeros [4:0] $end
$var wire 32 ~ s [31:0] $end
$var wire 25 !" frac_round [24:0] $end
$var wire 27 "" f4 [26:0] $end
$var wire 27 #" f3 [26:0] $end
$var wire 27 $" f2 [26:0] $end
$var wire 27 %" f1 [26:0] $end
$var wire 27 &" f0 [26:0] $end
$var wire 8 '" exponent [7:0] $end
$var reg 8 (" exp0 [7:0] $end
$var reg 27 )" frac0 [26:0] $end
$scope function final_result $end
$var reg 8 *" exponent [7:0] $end
$var reg 32 +" final_result [31:0] $end
$var reg 23 ," fraction [22:0] $end
$var reg 23 -" inf_nan_frac [22:0] $end
$var reg 1 ." is_inf $end
$var reg 1 /" is_nan $end
$var reg 1 0" overflow $end
$var reg 2 1" rm [1:0] $end
$var reg 1 2" sign $end
$upscope $end
$upscope $end
$upscope $end
$upscope $end
$enddefinitions $end
#0
$dumpvars
02"
b0 1"
00"
0/"
0."
b0 -"
b0 ,"
b0 +"
b0 *"
b0 )"
b0 ("
b0 '"
b0 &"
b0 %"
b0 $"
b0 #"
b0 ""
b0 !"
b0 ~
b11111 }
0|
b0 {
b0 z
b0 y
b0 x
0w
b0 v
b0 u
b0 t
b0 s
b0 r
b0 q
b0 p
b0 o
b0 n
b0 m
b0 l
b0 k
b0 j
b1111101 i
b0 h
b1110000000000000000101 g
1f
b101 e
b10111110100000100000000000000000 d
0c
0b
1a
b111100011000000000000000010001 `
0_
0^
1]
b100000100000000000000000 \
b11000000000000000010001 [
b101 Z
b111000000000000000010001 Y
b111000000000000000010001000000000000000000000 X
0W
0V
0U
0T
0S
b10111110100000100000000000000000 R
b100000100000000000000000 Q
b111100011000000000000000010001 P
b0 O
b0 N
b0 M
b0 L
b0 K
b1111101 J
b0 I
b100000100000000000000000 H
b1110000000000000000101 G
b0 F
b1111101 E
b0 D
0C
0B
b100000100000000000000000 A
0@
0?
b1110000000000000000101 >
b0 =
b0 <
b0 ;
0:
09
b0 8
07
b0 6
05
b0 4
b0 3
b0 2
b0 1
00
0/
b0 .
0-
b0 ,
b0 +
b10111110100000100000000000000000 *
b111100011000000000000000010001 )
1(
b0 '
1&
0%
1$
b10111110100000100000000000000000 #
b111100011000000000000000010001 "
b0 !
$end
#2
1%
#5
0$
#10
b100010010000000000000000101 <
b100010010000000000000000101 m
b100010010000000000000000101 t
b1110000000000000000101 u
b1110000000000000000101 4
b1110000000000000000101 O
b1110000000000000000101 s
b100000100000000000000000000 v
b100000100000000000000000 8
b100000100000000000000000 M
b100000100000000000000000 r
b1111101 =
b1111101 K
b1111101 j
1$
#15
0$
b1 '
b1 +
b1 F
#20
1w
b10010000000000000001 ,"
b111110100010010000000000000001 !
b111110100010010000000000000001 ,
b111110100010010000000000000001 ~
b111110100010010000000000000001 +"
b1111101 *"
b100010010000000000000001 !"
b1111101 '"
b100010010000000000000000101 )"
b1111101 ("
b100010010000000000000000101 &"
b100010010000000000000000101 %"
b100010010000000000000000101 $"
b100010010000000000000000101 #"
b100010010000000000000000101 ""
b0 }
b1 6
b1 N
b1 l
b100010010000000000000000101 2
b100010010000000000000000101 o
b100010010000000000000000101 y
b1111101 3
b1111101 n
b1111101 x
1$
#25
0$
b10 '
b10 +
b10 F
#30
b111110100010010000000000000000 !
b111110100010010000000000000000 ,
b111110100010010000000000000000 ~
b111110100010010000000000000000 +"
b10010000000000000000 ,"
b100010010000000000000000 !"
0w
b1 1"
b1 .
b1 q
b1 {
b10 6
b10 N
b10 l
1$
#35
0$
b11 '
b11 +
b11 F
#40
b111110100010010000000000000001 !
b111110100010010000000000000001 ,
b111110100010010000000000000001 ~
b111110100010010000000000000001 +"
b10010000000000000001 ,"
b100010010000000000000001 !"
1w
b10 1"
b11 6
b11 N
b11 l
b10 .
b10 q
b10 {
1$
#45
1?
1@
0$
0(
b0 '
b0 +
b0 F
#50
b111110100010010000000000000000 !
b111110100010010000000000000000 ,
b111110100010010000000000000000 ~
b111110100010010000000000000000 +"
b10010000000000000000 ,"
b100010010000000000000000 !"
0w
b11 1"
b11110101111111111111111011 <
b11110101111111111111111011 m
b11110101111111111111111011 t
b11 .
b11 q
b11 {
17
15
b0 6
b0 N
b0 l
1$
#55
0$
b1 '
b1 +
b1 F
#60
b1111100 *"
b1111100 '"
b1 }
b111101011111111111111110110 )"
b1111100 ("
b11101011111111111111111 ,"
b111101011111111111111110110 &"
b11110101111111111111111011 %"
b111101011111111111111111 !"
1w
b11110101111111111111111011 $"
b11110101111111111111111011 #"
b11110101111111111111111011 ""
b10111110011101011111111111111111 !
b10111110011101011111111111111111 ,
b10111110011101011111111111111111 ~
b10111110011101011111111111111111 +"
12"
b0 1"
b1 6
b1 N
b1 l
b11110101111111111111111011 2
b11110101111111111111111011 o
b11110101111111111111111011 y
1-
b0 .
b0 q
b0 {
1$
#65
0$
b10 '
b10 +
b10 F
#70
b1 1"
b1 .
b1 q
b1 {
b10 6
b10 N
b10 l
1$
#75
0$
b11 '
b11 +
b11 F
#80
b10111110011101011111111111111110 !
b10111110011101011111111111111110 ,
b10111110011101011111111111111110 ~
b10111110011101011111111111111110 +"
b11101011111111111111110 ,"
b111101011111111111111110 !"
0w
b10 1"
b11 6
b11 N
b11 l
b10 .
b10 q
b10 {
1$
#85
b100 >
b100 G
b100 g
1^
b10000000000000000000000000 X
b11000 Z
b111111111111111111111111 A
b111111111111111111111111 H
b111111111111111111111111 Q
b111111111111111111111111 \
b1111111 E
b1111111 J
b1111111 i
b100000000000000000000000 Y
b11000 e
b11111111111111111111111 [
0?
0@
b111111111111111111111111111111 d
0f
b10110011100000000000000000000000 `
0$
b10110011100000000000000000000000 #
b10110011100000000000000000000000 *
b10110011100000000000000000000000 R
b111111111111111111111111111111 "
b111111111111111111111111111111 )
b111111111111111111111111111111 P
1(
b0 '
b0 +
b0 F
#90
b11 1"
b111111111111111111111111100 <
b111111111111111111111111100 m
b111111111111111111111111100 t
b11 .
b11 q
b11 {
b100 u
b100 4
b100 O
b100 s
b111111111111111111111111000 v
b111111111111111111111111 8
b111111111111111111111111 M
b111111111111111111111111 r
07
b1111111 =
b1111111 K
b1111111 j
05
b0 6
b0 N
b0 l
1$
#95
0$
b1 '
b1 +
b1 F
#100
b111111111111111111111111100 )"
b0 }
b111111111111111111111111100 &"
b0 ,"
b111111111111111111111111100 %"
b1000000000000000000000000 !"
1w
b111111111111111111111111100 $"
b111111111111111111111111100 #"
b10000000 *"
b111111111111111111111111100 ""
b10000000 '"
b1111111 ("
b1000000000000000000000000000000 !
b1000000000000000000000000000000 ,
b1000000000000000000000000000000 ~
b1000000000000000000000000000000 +"
02"
b0 1"
b1 6
b1 N
b1 l
b111111111111111111111111100 2
b111111111111111111111111100 o
b111111111111111111111111100 y
b1111111 3
b1111111 n
b1111111 x
0-
b0 .
b0 q
b0 {
1$
#105
0$
b10 '
b10 +
b10 F
#110
b1111111 *"
b1111111 '"
b111111111111111111111111111111 !
b111111111111111111111111111111 ,
b111111111111111111111111111111 ~
b111111111111111111111111111111 +"
b11111111111111111111111 ,"
b111111111111111111111111 !"
0w
b1 1"
b1 .
b1 q
b1 {
b10 6
b10 N
b10 l
1$
#115
0$
b11 '
b11 +
b11 F
#120
b10000000 *"
b10000000 '"
b1000000000000000000000000000000 !
b1000000000000000000000000000000 ,
b1000000000000000000000000000000 ~
b1000000000000000000000000000000 +"
b0 ,"
b1000000000000000000000000 !"
1w
b10 1"
b11 6
b11 N
b11 l
b10 .
b10 q
b10 {
1$
#125
1@
0$
0(
b0 '
b0 +
b0 F
#130
b1111111 *"
b1111111 '"
b111111111111111111111111111111 !
b111111111111111111111111111111 ,
b111111111111111111111111111111 ~
b111111111111111111111111111111 +"
b11111111111111111111111 ,"
b111111111111111111111111 !"
0w
b11 1"
b111111111111111111111110100 <
b111111111111111111111110100 m
b111111111111111111111110100 t
b11 .
b11 q
b11 {
17
b0 6
b0 N
b0 l
1$
#135
0$
b1 '
b1 +
b1 F
#140
b111111111111111111111110100 )"
b1111111 *"
b111111111111111111111110100 &"
b1111111 '"
b111111111111111111111111111110 !
b111111111111111111111111111110 ,
b111111111111111111111111111110 ~
b111111111111111111111111111110 +"
b11111111111111111111110 ,"
b111111111111111111111110100 %"
b111111111111111111111110100 $"
b111111111111111111111110 !"
0w
b111111111111111111111110100 #"
b111111111111111111111110100 ""
b0 1"
b1 6
b1 N
b1 l
b111111111111111111111110100 2
b111111111111111111111110100 o
b111111111111111111111110100 y
b0 .
b0 q
b0 {
1$
#145
0$
b10 '
b10 +
b10 F
#150
b1 1"
b1 .
b1 q
b1 {
b10 6
b10 N
b10 l
1$
#155
0$
b11 '
b11 +
b11 F
#160
b111111111111111111111111111111 !
b111111111111111111111111111111 ,
b111111111111111111111111111111 ~
b111111111111111111111111111111 +"
b11111111111111111111111 ,"
b111111111111111111111111 !"
1w
b10 1"
b11 6
b11 N
b11 l
b10 .
b10 q
b10 {
1$
#165
b0 D
b0 I
b0 h
0B
b100000000000000000000000000 >
b100000000000000000000000000 G
b100000000000000000000000000 g
1C
b10000000000000000000000000000000000000000000000000 X
0@
1U
1S
b0 Z
1_
b100000000000000000000000 A
b100000000000000000000000 H
b100000000000000000000000 Q
b100000000000000000000000 \
b11111111 E
b11111111 J
b11111111 i
1c
1b
b0 e
b10000000000000000000000 [
b1111111100000000000000000000000 `
b1111111100000000000000000000000 d
0$
b1111111100000000000000000000000 #
b1111111100000000000000000000000 *
b1111111100000000000000000000000 R
b1111111100000000000000000000000 "
b1111111100000000000000000000000 )
b1111111100000000000000000000000 P
b0 '
b0 +
b0 F
#170
b111111111111111111111111111110 !
b111111111111111111111111111110 ,
b111111111111111111111111111110 ~
b111111111111111111111111111110 +"
b11111111111111111111110 ,"
b111111111111111111111110 !"
0w
b11 1"
b1000000000000000000000000000 <
b1000000000000000000000000000 m
b1000000000000000000000000000 t
b11 .
b11 q
b11 {
b100000000000000000000000000 u
b100000000000000000000000000 4
b100000000000000000000000000 O
b100000000000000000000000000 s
b100000000000000000000000000 v
b100000000000000000000000 8
b100000000000000000000000 M
b100000000000000000000000 r
07
b11111111 =
b11111111 K
b11111111 j
1:
b0 6
b0 N
b0 l
1$
#175
b10000000000000000000000 D
b10000000000000000000000 I
b10000000000000000000000 h
1B
1@
0$
1(
#180
b0 &"
b0 %"
b0 $"
b0 #"
b0 ,"
b0 *"
b0 ""
b0 '"
b0 !"
b0 <
b0 m
b0 t
b11111 }
b0 ("
b0 )"
b1111111100000000000000000000000 !
b1111111100000000000000000000000 ,
b1111111100000000000000000000000 ~
b1111111100000000000000000000000 +"
1."
b0 1"
17
b10000000000000000000000 ;
b10000000000000000000000 L
b10000000000000000000000 k
19
b1000000000000000000000000000 2
b1000000000000000000000000000 o
b1000000000000000000000000000 y
b11111111 3
b11111111 n
b11111111 x
10
b0 .
b0 q
b0 {
1$
#185
1B
b10000000111111111111111100 >
b10000000111111111111111100 G
b10000000111111111111111100 g
1T
b1 Z
0C
b1000000011111111111111110000000000000000000000000 X
0U
0S
b11000000000000000001111 D
b11000000000000000001111 I
b11000000000000000001111 h
b100000001111111111111111 Y
0_
0^
b111000000000000000001111 A
b111000000000000000001111 H
b111000000000000000001111 Q
b111000000000000000001111 \
b11111111 E
b11111111 J
b11111111 i
1c
0b
b1 e
b11000000000000000001111 [
0@
b1111111000000001111111111111111 `
1f
b1111111111000000000000000001111 d
0$
b1111111111000000000000000001111 #
b1111111111000000000000000001111 *
b1111111111000000000000000001111 R
b1111111000000001111111111111111 "
b1111111000000001111111111111111 )
b1111111000000001111111111111111 P
0(
#190
b11111111110000000000000000000000 !
b11111111110000000000000000000000 ,
b11111111110000000000000000000000 ~
b11111111110000000000000000000000 +"
b10000000000000000000000 -"
1/"
b1001000001000000000001110100 <
b1001000001000000000001110100 m
b1001000001000000000001110100 t
b0 2
b0 o
b0 y
b10000000000000000000000 1
b10000000000000000000000 p
b10000000000000000000000 z
1/
b10000000111111111111111100 u
b10000000111111111111111100 4
b10000000111111111111111100 O
b10000000111111111111111100 s
b111000000000000000001111000 v
b111000000000000000001111 8
b111000000000000000001111 M
b111000000000000000001111 r
07
b11000000000000000001111 ;
b11000000000000000001111 L
b11000000000000000001111 k
0:
1$
#195
0B
b111111111111111111111111000 >
b111111111111111111111111000 G
b111111111111111111111111000 g
0T
b0 Z
b11111111111111111111111100000000000000000000000000 X
b0 D
b0 I
b0 h
b111111111111111111111111 A
b111111111111111111111111 H
b111111111111111111111111 Q
b111111111111111111111111 \
b11111110 E
b11111110 J
b11111110 i
0c
b0 e
b111111111111111111111111 Y
b11111111111111111111111 [
0f
b1111111011111111111111111111111 d
b1111111011111111111111111111111 `
0$
b1111111011111111111111111111111 #
b1111111011111111111111111111111 *
b1111111011111111111111111111111 R
b1111111011111111111111111111111 "
b1111111011111111111111111111111 )
b1111111011111111111111111111111 P
