SingleCycle/single_cycle_cpu.v
module single_cycle_cpu(
  input        clk, clrn,
  input[31:0]  inst,
  input[31:0]  mem,
  output[31:0] pc,
  output       wmem,
  output[31:0] alu, data
);

// instruction
wire[5:0] op    = inst[31:26];
wire[4:0] rs    = inst[25:21];
wire[4:0] rt    = inst[20:16];
wire[4:0] rd    = inst[15:11];
wire[5:0] func  = inst[5:0];
wire[15:0] imm  = inst[15:0];
wire[25:0] addr = inst[25:0];
// ALU
reg[31:0] alu_out;
wire[31:0] alu_in_a, alu_in_b;
wire[31:0] shift_amount = {27'b0, inst[10:6]};
wire alu_out_zero = (alu_out == 32'b0);
assign alu = alu_out;
// control signals
wire[3:0] aluc;
wire[1:0] pcsrc;
wire wmem, wreg, regrt, m2reg, shift, aluimm, jal, sext;
// program counter
reg[31:0] program_counter;
wire[31:0] pc_plus_4 = program_counter + 32'd4;
wire[15:0] imm_sign = {16{sext&imm[15]}};
wire[31:0] branch_pc = pc_plus_4 + {imm_sign[13:0], imm, 2'b00}; 
wire[31:0] jump_pc = {pc_plus_4[31:28], addr, 2'b00};
assign pc = program_counter;
// register file
wire[31:0] qa, qb; // output
wire[4:0]  reg_write_port = (jal ? {5{jal}} : (regrt ? rt : rd));
wire[31:0] reg_write_data = (jal ? pc_plus_4 : (m2reg ? mem : alu_out));
regfile regfile0(rs, rt, reg_write_data, reg_write_port, wreg, clk, clrn, qa, qb);
assign data = qb;

// program counter
always @(posedge clk or negedge clrn) begin
  if(!clrn)
    program_counter <= 32'b0;
  else
    if(pcsrc == 2'd0)
      program_counter <= pc_plus_4;
    else if(pcsrc == 2'd1)
      program_counter <= branch_pc;
    else if(pcsrc == 2'd2)
      program_counter <= qa;
    else if(pcsrc == 2'd3)
      program_counter <= jump_pc;
end

// ALU
assign alu_in_a = (shift ? shift_amount : qa);
assign alu_in_b = (aluimm ? {imm_sign, imm} : qb);
always @* begin
  casex(aluc)
    4'bx000: alu_out <= alu_in_a + alu_in_b;
    4'bx100: alu_out <= alu_in_a - alu_in_b;
    4'bx001: alu_out <= alu_in_a & alu_in_b;
    4'bx101: alu_out <= alu_in_a | alu_in_b;
    4'bx010: alu_out <= alu_in_a ^ alu_in_b;
    4'bx110: alu_out <= {alu_in_b[15:0], 16'b0};
    4'b0011: alu_out <= alu_in_b << shift_amount;
    4'b0111: alu_out <= alu_in_b >> shift_amount;
    4'b1111: alu_out <= $signed(alu_in_b) >>> shift_amount;
    default: alu_out <= 32'b0;
  endcase
end

// control unit
single_cycle_control_unit control_unit(
  .op(op), .func(func), .z(alu_out_zero),
  .wmem(wmem), .wreg(wreg), .regrt(regrt),
  .m2reg(m2reg), .aluc(aluc), .shift(shift),
  .aluimm(aluimm), .pcsrc(pcsrc), .jal(jal), .sext(sext));

endmodule


module single_cycle_control_unit(
  input[5:0]  op, func,
  input       z,      // ALU zero flag
  output      wmem,   // write enable of Data memory
  output      wreg,   // write enable of register file
  output      regrt,  // use rt as a destination register
  output      m2reg,  // select Data memory out instead of ALU out
  output[3:0] aluc,   // ALU control signal
  output      shift,  // use inst[10:6] instead of rs as a ALU input (shift amount)
  output      aluimm, // use inst[15:0] instead of rd as a ALU input (immediate value)
  output[1:0] pcsrc,  // selector of program counter source
  output      jal,    // jump and link (function call, $31 <= PC; PC <= target) instruction
  output      sext    // sign extension of immediate value
);

// op decode
wire i_add  = (op == 6'b000000) & (func == 6'b100000); // add
wire i_sub  = (op == 6'b000000) & (func == 6'b100010); // sub
wire i_and  = (op == 6'b000000) & (func == 6'b100100); // and
wire i_or   = (op == 6'b000000) & (func == 6'b100101); // or
wire i_xor  = (op == 6'b000000) & (func == 6'b100110); // xor
wire i_sll  = (op == 6'b000000) & (func == 6'b000000); // shift left logical
wire i_srl  = (op == 6'b000000) & (func == 6'b000010); // shift right logical
wire i_sra  = (op == 6'b000000) & (func == 6'b000011); // shift right arithmetic
wire i_jr   = (op == 6'b000000) & (func == 6'b001000); // jump register
wire i_addi = (op == 6'b001000); // add immediate
wire i_andi = (op == 6'b001100); // and immediate
wire i_ori  = (op == 6'b001101); // or immediate
wire i_xori = (op == 6'b001110); // xor immediate
wire i_lw   = (op == 6'b100011); // load word
wire i_sw   = (op == 6'b101011); // store word
wire i_beq  = (op == 6'b000100); // branch equal
wire i_bne  = (op == 6'b000101); // branch not equal
wire i_lui  = (op == 6'b001111); // load upper immediate
wire i_j    = (op == 6'b000010); // jump
wire i_jal  = (op == 6'b000011); // jump and link

assign regrt    = i_addi | i_andi | i_ori | i_xori | i_lw | i_lui;
assign jal      = i_jal;
assign m2reg    = i_lw;
assign wmem     = i_sw;
assign aluc[3]  = i_sra;
assign aluc[2]  = i_sub | i_or | i_srl | i_sra | i_ori | i_lui;
assign aluc[1]  = i_xor | i_sll| i_srl | i_sra | i_lui | i_xori | i_beq | i_bne;
assign aluc[0]  = i_and | i_or | i_sll | i_srl | i_sra | i_andi | i_ori;
assign shift    = i_sll | i_srl| i_sra;
assign aluimm   = i_addi | i_andi | i_ori | i_xori | i_lw | i_lui | i_sw;
assign sext     = i_addi | i_lw | i_sw | i_beq | i_bne;
assign pcsrc[1] = i_jr | i_j | i_jal;
assign pcsrc[0] = i_beq & z | i_bne & ~z | i_j | i_jal;
assign wreg     = i_add | i_sub | i_and | i_or | i_xor | i_sll | i_srl | i_sra |
                  i_addi | i_andi | i_ori | i_xori | i_lw | i_lui | i_jal;

endmodule





module scinstmem (a,inst);               // instruction memory, rom
    input  [31:0] a;                     // address
    output [31:0] inst;                  // instruction
    wire   [31:0] rom [0:31];            // rom cells: 32 words * 32 bits
    // rom[word_addr] = instruction      // (pc) label   instruction
    assign rom[5'h00] = 32'h3c010000;    // (00) main:   lui  $1, 0
    assign rom[5'h01] = 32'h34240050;    // (04)         ori  $4, $1, 80
    assign rom[5'h02] = 32'h20050004;    // (08)         addi $5, $0,  4
    assign rom[5'h03] = 32'h0c000018;    // (0c) call:   jal  sum
    assign rom[5'h04] = 32'hac820000;    // (10)         sw   $2, 0($4)
    assign rom[5'h05] = 32'h8c890000;    // (14)         lw   $9, 0($4)
    assign rom[5'h06] = 32'h01244022;    // (18)         sub  $8, $9, $4
    assign rom[5'h07] = 32'h20050003;    // (1c)         addi $5, $0,  3
    assign rom[5'h08] = 32'h20a5ffff;    // (20) loop2:  addi $5, $5, -1
    assign rom[5'h09] = 32'h34a8ffff;    // (24)         ori  $8, $5, 0xffff
    assign rom[5'h0A] = 32'h39085555;    // (28)         xori $8, $8, 0x5555
    assign rom[5'h0B] = 32'h2009ffff;    // (2c)         addi $9, $0, -1
    assign rom[5'h0C] = 32'h312affff;    // (30)         andi $10,$9, 0xffff
    assign rom[5'h0D] = 32'h01493025;    // (34)         or   $6, $10, $9
    assign rom[5'h0E] = 32'h01494026;    // (38)         xor  $8, $10, $9
    assign rom[5'h0F] = 32'h01463824;    // (3c)         and  $7, $10, $6
    assign rom[5'h10] = 32'h10a00001;    // (40)         beq  $5, $0, shift
    assign rom[5'h11] = 32'h08000008;    // (44)         j    loop2
    assign rom[5'h12] = 32'h2005ffff;    // (48) shift:  addi $5, $0, -1
    assign rom[5'h13] = 32'h000543c0;    // (4c)         sll  $8, $5, 15
    assign rom[5'h14] = 32'h00084400;    // (50)         sll  $8, $8, 16
    assign rom[5'h15] = 32'h00084403;    // (54)         sra  $8, $8, 16
    assign rom[5'h16] = 32'h000843c2;    // (58)         srl  $8, $8, 15
    assign rom[5'h17] = 32'h08000017;    // (5c) finish: j    finish
    assign rom[5'h18] = 32'h00004020;    // (60) sum:    add  $8, $0, $0
    assign rom[5'h19] = 32'h8c890000;    // (64) loop:   lw   $9, 0($4)
    assign rom[5'h1A] = 32'h20840004;    // (68)         addi $4, $4,  4
    assign rom[5'h1B] = 32'h01094020;    // (6c)         add  $8, $8, $9
    assign rom[5'h1C] = 32'h20a5ffff;    // (70)         addi $5, $5, -1
    assign rom[5'h1D] = 32'h14a0fffb;    // (74)         bne  $5, $0, loop
    assign rom[5'h1E] = 32'h00081000;    // (78)         sll  $2, $8, 0
    assign rom[5'h1F] = 32'h03e00008;    // (7c)         jr   $31
    assign inst = rom[a[6:2]];           // use word address to read rom
endmodule

module scdatamem (clk,dataout,datain,addr,we);           // data memory, ram
    input         clk;                   // clock
    input         we;                    // write enable
    input  [31:0] datain;                // data in (to memory)
    input  [31:0] addr;                  // ram address
    output [31:0] dataout;               // data out (from memory)
    reg    [31:0] ram [0:31];            // ram cells: 64 words * 32 bits
    assign dataout = ram[addr[6:2]];     // use word address to read ram
    always @ (posedge clk)
        if (we) ram[addr[6:2]] = datain; // use word address to write ram
    integer i;
    initial begin                        // initialize memory
        for (i = 0; i < 32; i = i + 1)
            ram[i] = 0;
        // ram[word_addr] = data         // (byte_addr) item in data array
        ram[5'h14] = 32'h000000a3;       // (50)  data[0]    0 +  A3 =  A3
        ram[5'h15] = 32'h00000027;       // (54)  data[1]   a3 +  27 =  ca
        ram[5'h16] = 32'h00000079;       // (58)  data[2]   ca +  79 = 143
        ram[5'h17] = 32'h00000115;       // (5c)  data[3]  143 + 115 = 258
        // ram[5'h18] should be 0x00000258, the sum stored by sw instruction
    end
endmodule

SingleCycle/register_file.v
module regfile(
  input [4:0]  rna, rnb,
  input [31:0] d,
  input [4:0]  wn,
  input        we,
  input        clk, clrn,
  output[31:0] qa, qb
);

reg[31:0] register[1:31];
assign qa = (rna == 0) ? 0 : register[rna];
assign qb = (rnb == 0) ? 0 : register[rnb];
integer i;
always @(posedge clk or negedge clrn) begin
  if(!clrn)
    for(i = 0; i < 32; i = i + 1)
      register[i] <= 0;
    else
      if((wn != 0) && we)
        register[wn] <= d;
end
endmodule

SingleCycle/single_cycle_cpu_tb.v
`timescale 1ns/1ns

module single_cycle_cpu_tb;

reg clk, clrn;
wire[31:0] pc, inst, aluout, memout, data;
wire wmem;
single_cycle_cpu sccpu(clk, clrn, inst, memout, pc, wmem, aluout, data);
scinstmem imem(pc, inst);
scdatamem dmem(clk, memout, data, aluout, wmem);

initial begin
  clk = 1;
  clrn = 0;
  #1 clrn = 1;
  #140 $finish;
end
initial begin
  $dumpfile("single_cycle_cpu.vcd");
  $dumpvars;
end
always #1 clk = !clk;

endmodule

SingleCycle/single_cycle_cpu.vcd
$date
	Sun May 10 00:54:23 2020
$end
$version
	Icarus Verilog
$end
$timescale
	1ns
$end
$scope module single_cycle_cpu_tb $end
$var wire 1 ! wmem $end
$var wire 32 " pc [31:0] $end
$var wire 32 # memout [31:0] $end
$var wire 32 $ inst [31:0] $end
$var wire 32 % data [31:0] $end
$var wire 32 & aluout [31:0] $end
$var reg 1 ' clk $end
$var reg 1 ( clrn $end
$scope module dmem $end
$var wire 1 ' clk $end
$var wire 32 ) dataout [31:0] $end
$var wire 1 ! we $end
$var wire 32 * datain [31:0] $end
$var wire 32 + addr [31:0] $end
$var integer 32 , i [31:0] $end
$upscope $end
$scope module imem $end
$var wire 32 - inst [31:0] $end
$var wire 32 . a [31:0] $end
$upscope $end
$scope module sccpu $end
$var wire 32 / alu [31:0] $end
$var wire 1 ' clk $end
$var wire 1 ( clrn $end
$var wire 32 0 data [31:0] $end
$var wire 32 1 inst [31:0] $end
$var wire 32 2 mem [31:0] $end
$var wire 32 3 pc [31:0] $end
$var wire 1 4 wreg $end
$var wire 1 ! wmem $end
$var wire 32 5 shift_amount [31:0] $end
$var wire 1 6 shift $end
$var wire 1 7 sext $end
$var wire 5 8 rt [4:0] $end
$var wire 5 9 rs [4:0] $end
$var wire 1 : regrt $end
$var wire 5 ; reg_write_port [4:0] $end
$var wire 32 < reg_write_data [31:0] $end
$var wire 5 = rd [4:0] $end
$var wire 32 > qb [31:0] $end
$var wire 32 ? qa [31:0] $end
$var wire 2 @ pcsrc [1:0] $end
$var wire 32 A pc_plus_4 [31:0] $end
$var wire 6 B op [5:0] $end
$var wire 1 C m2reg $end
$var wire 32 D jump_pc [31:0] $end
$var wire 1 E jal $end
$var wire 16 F imm_sign [15:0] $end
$var wire 16 G imm [15:0] $end
$var wire 6 H func [5:0] $end
$var wire 32 I branch_pc [31:0] $end
$var wire 1 J aluimm $end
$var wire 4 K aluc [3:0] $end
$var wire 1 L alu_out_zero $end
$var wire 32 M alu_in_b [31:0] $end
$var wire 32 N alu_in_a [31:0] $end
$var wire 26 O addr [25:0] $end
$var reg 32 P alu_out [31:0] $end
$var reg 32 Q program_counter [31:0] $end
$scope module control_unit $end
$var wire 1 J aluimm $end
$var wire 6 R func [5:0] $end
$var wire 1 S i_add $end
$var wire 1 T i_and $end
$var wire 1 U i_jr $end
$var wire 1 V i_or $end
$var wire 1 W i_sll $end
$var wire 1 X i_sra $end
$var wire 1 Y i_srl $end
$var wire 1 Z i_sub $end
$var wire 1 [ i_xor $end
$var wire 1 E jal $end
$var wire 1 C m2reg $end
$var wire 6 \ op [5:0] $end
$var wire 1 : regrt $end
$var wire 1 7 sext $end
$var wire 1 6 shift $end
$var wire 1 ! wmem $end
$var wire 1 4 wreg $end
$var wire 1 L z $end
$var wire 2 ] pcsrc [1:0] $end
$var wire 1 ^ i_xori $end
$var wire 1 _ i_sw $end
$var wire 1 ` i_ori $end
$var wire 1 a i_lw $end
$var wire 1 b i_lui $end
$var wire 1 c i_jal $end
$var wire 1 d i_j $end
$var wire 1 e i_bne $end
$var wire 1 f i_beq $end
$var wire 1 g i_andi $end
$var wire 1 h i_addi $end
$var wire 4 i aluc [3:0] $end
$upscope $end
$scope module regfile0 $end
$var wire 1 ' clk $end
$var wire 1 ( clrn $end
$var wire 32 j d [31:0] $end
$var wire 5 k rna [4:0] $end
$var wire 5 l rnb [4:0] $end
$var wire 1 4 we $end
$var wire 5 m wn [4:0] $end
$var wire 32 n qb [31:0] $end
$var wire 32 o qa [31:0] $end
$var integer 32 p i [31:0] $end
$upscope $end
$upscope $end
$upscope $end
$enddefinitions $end
#0
$dumpvars
b100000 p
b0 o
b0 n
b1 m
b1 l
b0 k
b0 j
b110 i
0h
0g
0f
0e
0d
0c
1b
0a
0`
0_
0^
b0 ]
b1111 \
0[
0Z
0Y
0X
0W
0V
0U
0T
0S
b0 R
b0 Q
b0 P
b10000000000000000 O
b0 N
b0 M
1L
b110 K
1J
b100 I
b0 H
b0 G
b0 F
0E
b1000000000000000000 D
0C
b1111 B
b100 A
b0 @
b0 ?
b0 >
b0 =
b0 <
b1 ;
1:
b0 9
b1 8
07
06
b0 5
14
b0 3
b0 2
b111100000000010000000000000000 1
b0 0
b0 /
b0 .
b111100000000010000000000000000 -
b100000 ,
b0 +
b0 *
b0 )
0(
1'
b0 &
b0 %
b111100000000010000000000000000 $
b0 #
b0 "
0!
$end
#1
0'
1(
#2
b1010000 <
b1010000 j
b10100011 #
b10100011 )
b10100011 2
0L
b1010000 &
b1010000 +
b1010000 /
b1010000 P
14
1J
b100 ;
b100 m
b101 K
b101 i
1:
b1010000 M
1`
0b
b1101 B
b1101 \
b1 9
b1 k
b100 8
b100 l
b10000 H
b10000 R
b1010000 G
b100100000000000101000000 D
b1001000000000001010000 O
b1 5
b110100001001000000000001010000 $
b110100001001000000000001010000 -
b110100001001000000000001010000 1
b101001000 I
b1000 A
b100 "
b100 .
b100 3
b100 Q
1'
#3
0'
#4
b100 <
b100 j
b0 #
b0 )
b0 2
0L
b100 &
b100 +
b100 /
b100 P
14
1J
17
1:
b101 ;
b101 m
b0 K
b0 i
b100 M
1h
0`
b1000 B
b1000 \
b0 9
b0 k
b101 8
b101 l
b100 H
b100 R
b100 G
b101000000000000010000 D
b1010000000000000100 O
b0 5
b0 %
b0 *
b0 0
b0 >
b0 n
b100000000001010000000000000100 $
b100000000001010000000000000100 -
b100000000001010000000000000100 1
b11100 I
b1100 A
b1000 "
b1000 .
b1000 3
b1000 Q
1'
#5
0'
#6
1L
b0 &
b0 +
b0 /
b0 P
0J
0:
07
b11 @
b11 ]
b10000 <
b10000 j
b11111 ;
b11111 m
b0 M
0h
1E
1c
b11 B
b11 \
b0 8
b0 l
b11000 H
b11000 R
b11000 G
b1100000 D
b11000 O
b1100000000000000000000011000 $
b1100000000000000000000011000 -
b1100000000000000000000011000 1
b0 %
b0 *
b0 0
b0 >
b0 n
b1110000 I
b10000 A
b1100 "
b1100 .
b1100 3
b1100 Q
1'
#7
0'
#8
14
b0 @
b0 ]
b1000 ;
b1000 m
1S
0E
0c
b0 B
b0 \
b1000 =
b100000 H
b100000 R
b100000000100000 G
b10000000010000000 D
b100000000100000 O
b0 <
b0 j
b100000000100000 $
b100000000100000 -
b100000000100000 1
b10000000011100100 I
b1100100 A
b1100000 "
b1100000 .
b1100000 3
b1100000 Q
1'
#9
0'
#10
b10100011 <
b10100011 j
b10100011 #
b10100011 )
b10100011 2
0L
b1010000 &
b1010000 +
b1010000 /
b1010000 P
17
1J
1:
b1010000 N
b1001 ;
b1001 m
b1010000 ?
b1010000 o
0S
1C
1a
b100011 B
b100011 \
b100 9
b100 k
b1001 8
b1001 l
b0 =
b0 H
b0 R
b0 G
b10001001000000000000000000 D
b100010010000000000000000 O
b10001100100010010000000000000000 $
b10001100100010010000000000000000 -
b10001100100010010000000000000000 1
b1101000 I
b1101000 A
b1100100 "
b1100100 .
b1100100 3
b1100100 Q
1'
#11
0'
#12
b100111 #
b100111 )
b100111 2
b1010100 &
b1010100 +
b1010100 /
b1010100 P
14
1J
b1010100 <
b1010100 j
1:
b100 ;
b100 m
b100 M
1h
0C
0a
b1000 B
b1000 \
b100 8
b100 l
b100 H
b100 R
b100 G
b10000100000000000000010000 D
b100001000000000000000100 O
b1010000 %
b1010000 *
b1010000 0
b1010000 >
b1010000 n
b100000100001000000000000000100 $
b100000100001000000000000000100 -
b100000100001000000000000000100 1
b1111100 I
b1101100 A
b1101000 "
b1101000 .
b1101000 3
b1101000 Q
1'
#13
0'
#14
b10100011 <
b10100011 j
b0 #
b0 )
b0 2
b10100011 &
b10100011 +
b10100011 /
b10100011 P
14
0J
0:
07
b1000 ;
b1000 m
1S
b10100011 M
0h
b0 B
b0 \
b1000 9
b1000 k
b1001 8
b1001 l
b1000 =
b100000 H
b100000 R
b100000000100000 G
b100001001010000000010000000 D
b1000010010100000000100000 O
b0 N
b1000010010100000000100000 $
b1000010010100000000100000 -
b1000010010100000000100000 1
b0 ?
b0 o
b10100011 %
b10100011 *
b10100011 0
b10100011 >
b10100011 n
b10000000011110000 I
b1110000 A
b1101100 "
b1101100 .
b1101100 3
b1101100 Q
1'
#15
0'
#16
b11 <
b11 j
b11 &
b11 +
b11 /
b11 P
1J
b1111111111111111 F
1:
17
b11111111111111111111111111111111 M
b101 ;
b101 m
b100 %
b100 *
b100 0
b100 >
b100 n
0S
b100 N
1h
b1000 B
b1000 \
b101 9
b101 k
b101 8
b101 l
b11111 =
b111111 H
b111111 R
b1111111111111111 G
b10100101111111111111111100 D
b101001011111111111111111 O
b11111 5
b100 ?
b100 o
b100000101001011111111111111111 $
b100000101001011111111111111111 -
b100000101001011111111111111111 1
b1110000 I
b1110100 A
b1110000 "
b1110000 .
b1110000 3
b1110000 Q
1'
#17
0'
#18
b11 &
b11 +
b11 /
b11 P
04
0J
0:
b1 @
b1 ]
b11111 ;
b11111 m
b10 K
b10 i
b0 M
0h
1e
b101 B
b101 \
b0 8
b0 l
b111011 H
b111011 R
b1111111111111011 G
b10100000111111111111101100 D
b101000001111111111111011 O
b11 N
b10100101000001111111111111011 $
b10100101000001111111111111011 -
b10100101000001111111111111011 1
b11 ?
b11 o
b0 %
b0 *
b0 0
b0 >
b0 n
b1100100 I
b1111000 A
b1110100 "
b1110100 .
b1110100 3
b1110100 Q
1'
#19
0'
#20
b100111 #
b100111 )
b100111 2
b1010100 &
b1010100 +
b1010100 /
b1010100 P
b0 @
b0 ]
14
1J
b100111 <
b100111 j
1:
b1010100 N
b0 M
b1001 ;
b1001 m
b0 F
17
b0 K
b0 i
b1010100 ?
b1010100 o
b10100011 %
b10100011 *
b10100011 0
b10100011 >
b10100011 n
1C
1a
0e
b100011 B
b100011 \
b100 9
b100 k
b1001 8
b1001 l
b0 =
b0 H
b0 R
b0 G
b10001001000000000000000000 D
b100010010000000000000000 O
b0 5
b10001100100010010000000000000000 $
b10001100100010010000000000000000 -
b10001100100010010000000000000000 1
b1101000 I
b1101000 A
b1100100 "
b1100100 .
b1100100 3
b1100100 Q
1'
#21
0'
#22
b1111001 #
b1111001 )
b1111001 2
b1011000 &
b1011000 +
b1011000 /
b1011000 P
14
1J
b1011000 <
b1011000 j
1:
b100 ;
b100 m
b100 M
1h
0C
0a
b1000 B
b1000 \
b100 8
b100 l
b100 H
b100 R
b100 G
b10000100000000000000010000 D
b100001000000000000000100 O
b100000100001000000000000000100 $
b100000100001000000000000000100 -
b100000100001000000000000000100 1
b1010100 %
b1010100 *
b1010100 0
b1010100 >
b1010100 n
b1111100 I
b1101100 A
b1101000 "
b1101000 .
b1101000 3
b1101000 Q
1'
#23
0'
#24
b11001010 <
b11001010 j
b0 #
b0 )
b0 2
b11001010 &
b11001010 +
b11001010 /
b11001010 P
14
0J
0:
07
b1000 ;
b1000 m
1S
b100111 M
b10100011 N
0h
b0 B
b0 \
b1000 9
b1000 k
b1001 8
b1001 l
b1000 =
b100000 H
b100000 R
b100000000100000 G
b100001001010000000010000000 D
b1000010010100000000100000 O
b10100011 ?
b10100011 o
b100111 %
b100111 *
b100111 0
b100111 >
b100111 n
b1000010010100000000100000 $
b1000010010100000000100000 -
b1000010010100000000100000 1
b10000000011110000 I
b1110000 A
b1101100 "
b1101100 .
b1101100 3
b1101100 Q
1'
#25
0'
#26
b10 <
b10 j
b10 &
b10 +
b10 /
b10 P
1J
b1111111111111111 F
1:
17
b11111111111111111111111111111111 M
b101 ;
b101 m
b11 %
b11 *
b11 0
b11 >
b11 n
0S
1h
b1000 B
b1000 \
b101 9
b101 k
b101 8
b101 l
b11111 =
b111111 H
b111111 R
b1111111111111111 G
b10100101111111111111111100 D
b101001011111111111111111 O
b11111 5
b11 N
b100000101001011111111111111111 $
b100000101001011111111111111111 -
b100000101001011111111111111111 1
b11 ?
b11 o
b1110000 I
b1110100 A
b1110000 "
b1110000 .
b1110000 3
b1110000 Q
1'
#27
0'
#28
b10 &
b10 +
b10 /
b10 P
04
0J
0:
b1 @
b1 ]
b11111 ;
b11111 m
b10 K
b10 i
b0 M
b10 N
0h
1e
b101 B
b101 \
b0 8
b0 l
b111011 H
b111011 R
b1111111111111011 G
b10100000111111111111101100 D
b101000001111111111111011 O
b10 ?
b10 o
b0 %
b0 *
b0 0
b0 >
b0 n
b10100101000001111111111111011 $
b10100101000001111111111111011 -
b10100101000001111111111111011 1
b1100100 I
b1111000 A
b1110100 "
b1110100 .
b1110100 3
b1110100 Q
1'
#29
0'
#30
b1111001 #
b1111001 )
b1111001 2
b1011000 &
b1011000 +
b1011000 /
b1011000 P
b0 @
b0 ]
14
1J
b1111001 <
b1111001 j
1:
b1011000 N
b0 M
b1001 ;
b1001 m
b0 F
17
b0 K
b0 i
b1011000 ?
b1011000 o
b100111 %
b100111 *
b100111 0
b100111 >
b100111 n
1C
1a
0e
b100011 B
b100011 \
b100 9
b100 k
b1001 8
b1001 l
b0 =
b0 H
b0 R
b0 G
b10001001000000000000000000 D
b100010010000000000000000 O
b0 5
b10001100100010010000000000000000 $
b10001100100010010000000000000000 -
b10001100100010010000000000000000 1
b1101000 I
b1101000 A
b1100100 "
b1100100 .
b1100100 3
b1100100 Q
1'
#31
0'
#32
b100010101 #
b100010101 )
b100010101 2
b1011100 &
b1011100 +
b1011100 /
b1011100 P
14
1J
b1011100 <
b1011100 j
1:
b100 ;
b100 m
b100 M
1h
0C
0a
b1000 B
b1000 \
b100 8
b100 l
b100 H
b100 R
b100 G
b10000100000000000000010000 D
b100001000000000000000100 O
b1011000 %
b1011000 *
b1011000 0
b1011000 >
b1011000 n
b100000100001000000000000000100 $
b100000100001000000000000000100 -
b100000100001000000000000000100 1
b1111100 I
b1101100 A
b1101000 "
b1101000 .
b1101000 3
b1101000 Q
1'
#33
0'
#34
b101000011 <
b101000011 j
b0 #
b0 )
b0 2
b101000011 &
b101000011 +
b101000011 /
b101000011 P
14
0J
0:
07
b1000 ;
b1000 m
1S
b1111001 M
0h
b0 B
b0 \
b1000 9
b1000 k
b1001 8
b1001 l
b1000 =
b100000 H
b100000 R
b100000000100000 G
b100001001010000000010000000 D
b1000010010100000000100000 O
b11001010 N
b1000010010100000000100000 $
b1000010010100000000100000 -
b1000010010100000000100000 1
b11001010 ?
b11001010 o
b1111001 %
b1111001 *
b1111001 0
b1111001 >
b1111001 n
b10000000011110000 I
b1110000 A
b1101100 "
b1101100 .
b1101100 3
b1101100 Q
1'
#35
0'
#36
b1 <
b1 j
b1 &
b1 +
b1 /
b1 P
1J
b1111111111111111 F
1:
17
b11111111111111111111111111111111 M
b101 ;
b101 m
b10 %
b10 *
b10 0
b10 >
b10 n
0S
b10 N
1h
b1000 B
b1000 \
b101 9
b101 k
b101 8
b101 l
b11111 =
b111111 H
b111111 R
b1111111111111111 G
b10100101111111111111111100 D
b101001011111111111111111 O
b11111 5
b10 ?
b10 o
b100000101001011111111111111111 $
b100000101001011111111111111111 -
b100000101001011111111111111111 1
b1110000 I
b1110100 A
b1110000 "
b1110000 .
b1110000 3
b1110000 Q
1'
#37
0'
#38
0L
b1 &
b1 +
b1 /
b1 P
04
0J
0:
b1 @
b1 ]
b11111 ;
b11111 m
b10 K
b10 i
b0 M
0h
1e
b101 B
b101 \
b0 8
b0 l
b111011 H
b111011 R
b1111111111111011 G
b10100000111111111111101100 D
b101000001111111111111011 O
b1 N
b10100101000001111111111111011 $
b10100101000001111111111111011 -
b10100101000001111111111111011 1
b1 ?
b1 o
b0 %
b0 *
b0 0
b0 >
b0 n
b1100100 I
b1111000 A
b1110100 "
b1110100 .
b1110100 3
b1110100 Q
1'
#39
0'
#40
b100010101 #
b100010101 )
b100010101 2
b1011100 &
b1011100 +
b1011100 /
b1011100 P
b0 @
b0 ]
14
1J
b100010101 <
b100010101 j
1:
b1011100 N
b0 M
b1001 ;
b1001 m
b0 F
17
b0 K
b0 i
b1011100 ?
b1011100 o
b1111001 %
b1111001 *
b1111001 0
b1111001 >
b1111001 n
1C
1a
0e
b100011 B
b100011 \
b100 9
b100 k
b1001 8
b1001 l
b0 =
b0 H
b0 R
b0 G
b10001001000000000000000000 D
b100010010000000000000000 O
b0 5
b10001100100010010000000000000000 $
b10001100100010010000000000000000 -
b10001100100010010000000000000000 1
b1101000 I
b1101000 A
b1100100 "
b1100100 .
b1100100 3
b1100100 Q
1'
#41
0'
#42
b0 #
b0 )
b0 2
b1100000 &
b1100000 +
b1100000 /
b1100000 P
14
1J
b1100000 <
b1100000 j
1:
b100 ;
b100 m
b100 M
1h
0C
0a
b1000 B
b1000 \
b100 8
b100 l
b100 H
b100 R
b100 G
b10000100000000000000010000 D
b100001000000000000000100 O
b100000100001000000000000000100 $
b100000100001000000000000000100 -
b100000100001000000000000000100 1
b1011100 %
b1011100 *
b1011100 0
b1011100 >
b1011100 n
b1111100 I
b1101100 A
b1101000 "
b1101000 .
b1101000 3
b1101000 Q
1'
#43
0'
#44
b1001011000 <
b1001011000 j
b1111001 #
b1111001 )
b1111001 2
b1001011000 &
b1001011000 +
b1001011000 /
b1001011000 P
14
0J
0:
07
b1000 ;
b1000 m
1S
b100010101 M
b101000011 N
0h
b0 B
b0 \
b1000 9
b1000 k
b1001 8
b1001 l
b1000 =
b100000 H
b100000 R
b100000000100000 G
b100001001010000000010000000 D
b1000010010100000000100000 O
b101000011 ?
b101000011 o
b100010101 %
b100010101 *
b100010101 0
b100010101 >
b100010101 n
b1000010010100000000100000 $
b1000010010100000000100000 -
b1000010010100000000100000 1
b10000000011110000 I
b1110000 A
b1101100 "
b1101100 .
b1101100 3
b1101100 Q
1'
#45
0'
#46
b0 <
b0 j
b0 #
b0 )
b0 2
1L
b0 &
b0 +
b0 /
b0 P
1J
b1111111111111111 F
1:
17
b11111111111111111111111111111111 M
b101 ;
b101 m
b1 %
b1 *
b1 0
b1 >
b1 n
0S
1h
b1000 B
b1000 \
b101 9
b101 k
b101 8
b101 l
b11111 =
b111111 H
b111111 R
b1111111111111111 G
b10100101111111111111111100 D
b101001011111111111111111 O
b11111 5
b1 N
b100000101001011111111111111111 $
b100000101001011111111111111111 -
b100000101001011111111111111111 1
b1 ?
b1 o
b1110000 I
b1110100 A
b1110000 "
b1110000 .
b1110000 3
b1110000 Q
1'
#47
0'
#48
1L
b0 &
b0 +
b0 /
b0 P
04
0J
0:
b11111 ;
b11111 m
b10 K
b10 i
b0 M
b0 N
0h
1e
b101 B
b101 \
b0 8
b0 l
b111011 H
b111011 R
b1111111111111011 G
b10100000111111111111101100 D
b101000001111111111111011 O
b0 ?
b0 o
b0 %
b0 *
b0 0
b0 >
b0 n
b10100101000001111111111111011 $
b10100101000001111111111111011 -
b10100101000001111111111111011 1
b1100100 I
b1111000 A
b1110100 "
b1110100 .
b1110100 3
b1110100 Q
1'
#49
0'
#50
b1001011000 <
b1001011000 j
b1111001 #
b1111001 )
b1111001 2
0L
b1001011000 &
b1001011000 +
b1001011000 /
b1001011000 P
14
16
b1001011000 M
b10 ;
b10 m
b0 F
07
b11 K
b11 i
b1001011000 %
b1001011000 *
b1001011000 0
b1001011000 >
b1001011000 n
1W
0e
b0 B
b0 \
b0 9
b0 k
b1000 8
b1000 l
b10 =
b0 H
b0 R
b1000000000000 G
b1000000100000000000000 D
b10000001000000000000 O
b0 5
b10000001000000000000 $
b10000001000000000000 -
b10000001000000000000 1
b100000001111100 I
b1111100 A
b1111000 "
b1111000 .
b1111000 3
b1111000 Q
1'
#51
0'
